discoauth/__init__.py
discoauth/__main__.py
discoauth/__version__.py
discoauth/common.py
discoauth/exceptions.py
discoauth/models.py
discoauth/url.py
discoauth/deprecated/common.py
discoauth/deprecated/models.py
discoauth/deprecated/url.py
discoauth-2.0.0.dist-info/LICENSE
discoauth-2.0.0.dist-info/METADATA
discoauth-2.0.0.dist-info/WHEEL
discoauth-2.0.0.dist-info/entry_points.txt
discoauth-2.0.0.dist-info/top_level.txt
discoauth-2.0.0.dist-info/RECORD
