Metadata-Version: 2.1
Name: discoauth
Version: 2.0.0
Summary: Discord OAuth, and Discord API, in one package
Author: Arcader717
License: MIT License
Project-URL: Homepage, https://github.com/disoauth/DiscoAuth
Project-URL: Bug Tracker, https://github.com/disoauth/DiscoAuth/issues
Project-URL: Repository, https://github.com/disoauth/DiscoAuth
Project-URL: Documentation, https://discoauth.readthedocs.io/en/latest/index.html
Project-URL: Changelog, https://github.com/disoauth/DiscoAuth/docs/CHANGELOG.rst
Keywords: Discord,OAuth2,oauth,auth,async,api
Classifier: Intended Audience :: Developers
Classifier: License :: OSI Approved :: MIT License
Classifier: Natural Language :: English
Classifier: Operating System :: OS Independent
Classifier: Topic :: Other/Nonlisted Topic
Classifier: Programming Language :: Python
Requires-Python: >=3.7
License-File: LICENSE
Requires-Dist: requests
Requires-Dist: click
Provides-Extra: pretty-cli
Requires-Dist: rich ; extra == 'pretty-cli'
